README.md
setup.cfg
setup.py
event_consumers/src/exceptions/__init__.py
event_consumers/src/exceptions/usi_exceptions.py
event_consumers/src/kafka_core/__init__.py
event_consumers/src/kafka_core/consumer_manager.py
event_consumers/src/kafka_core/kafka_stream_writer.py
event_consumers/src/kafka_core/kafka_util.py
event_consumers/src/kafka_core/ser_des_util.py
event_consumers/src/kafka_core/sink_task.py
event_consumers/src/logging/__init__.py
event_consumers/src/logging/logging_util.py
event_consumers/src/model/__init__.py
event_consumers/src/model/worker_dto.py
event_consumers/src/stream_writers/__init__.py
event_consumers/src/stream_writers/console_stream_writer.py
event_consumers/src/stream_writers/es_stream_writer.py
event_consumers/src/stream_writers/stream_writer.py
event_consumers/src/transformers/__init__.py
event_consumers/src/transformers/api_transformer.py
event_consumers/src/transformers/collection_transformer.py
event_consumers/src/transformers/entity_images_transformer.py
event_consumers/src/transformers/folder_transformer.py
event_consumers/src/transformers/fork_transformer.py
event_consumers/src/transformers/public_profile_transformer.py
event_consumers/src/transformers/request_transformer.py
event_consumers/src/transformers/response_transformer.py
event_consumers/src/transformers/test_transformer.py
event_consumers/src/transformers/transformer.py
event_consumers/src/transformers/users_transformer.py
event_consumers/src/transformers/workspace_slug_transformer.py
event_consumers/src/transformers/workspace_transformer.py
event_consumers/src/utility/__init__.py
event_consumers/src/utility/common_util.py
event_consumers/src/utility/config_manager.py
kafka_connect_dependency.egg-info/PKG-INFO
kafka_connect_dependency.egg-info/SOURCES.txt
kafka_connect_dependency.egg-info/dependency_links.txt
kafka_connect_dependency.egg-info/requires.txt
kafka_connect_dependency.egg-info/top_level.txt