Metadata-Version: 2.1
Name: kafka-connect-dependency
Version: 0.1.4
Summary: Library to run distributed Kafka Consumers using Ray
Home-page: UNKNOWN
Author: Search Dev
License: UNKNOWN
Keywords: ray,kafka,consumer
Platform: UNKNOWN
Requires-Python: >=3.7
